pylie/__init__.py
pylie/hmanifold/__init__.py
pylie/hmanifold/hmanifold.py
pylie/hmanifold/hmheavytop.py
pylie/hmanifold/hmnsphere.py
pylie/liealgebra/__init__.py
pylie/liealgebra/liealgebra.py
pylie/liegroup/__init__.py
pylie/liegroup/liegroup.py
pylie/solve/__init__.py
pylie/solve/solve.py
pylie/test/__init__.py
pylie/test/test_heavytop.py
pylie/test/test_so3.py
pylie/timestepper/__init__.py
pylie/timestepper/timestepper.py
pylie-0.4.0.dist-info/LICENSE
pylie-0.4.0.dist-info/METADATA
pylie-0.4.0.dist-info/WHEEL
pylie-0.4.0.dist-info/top_level.txt
pylie-0.4.0.dist-info/RECORD
