Metadata-Version: 2.1
Name: pylie
Version: 0.4.0
Summary: A Python package for solving ordinary differential equations evolving on non-linear manifolds
Home-page: https://github.com/jakobsen/pylie/
Author: Erik André Jakobsen
Author-email: erikaja@stud.ntnu.no
License: UNKNOWN
Project-URL: Bug Tracker, https://github.com/jakobsen/pylie/issues
Platform: UNKNOWN
Classifier: Programming Language :: Python :: 3
Classifier: License :: OSI Approved :: MIT License
Classifier: Operating System :: OS Independent
Requires-Python: >=3.6
License-File: LICENSE
Requires-Dist: numpy
Requires-Dist: scipy
